[{"modeltype":"Pattern_PAM","timecut":{"start":"21","end":"49","mindays":"10"},"k":1,"pctl":{"name":"P1_ProbReach","properties":"const N; const j; \nP = ? [F<=N y=j]\n","arguments":"-const N=200,j=0:1:23"},"result":{"j":"0","value":1},"$$hashKey":"object:3178"},{"modeltype":"Pattern_PAM","timecut":{"start":"21","end":"49","mindays":"10"},"k":1,"pctl":{"name":"P1_ProbReach","properties":"const N; const j; \nP = ? [F<=N y=j]\n","arguments":"-const N=200,j=0:1:23"},"result":{"j":"1","value":0},"$$hashKey":"object:3179"},{"modeltype":"Pattern_PAM","timecut":{"start":"21","end":"49","mindays":"10"},"k":1,"pctl":{"name":"P1_ProbReach","properties":"const N; const j; \nP = ? [F<=N y=j]\n","arguments":"-const N=200,j=0:1:23"},"result":{"j":"2","value":0.04281261706047415},"$$hashKey":"object:3180"},{"modeltype":"Pattern_PAM","timecut":{"start":"21","end":"49","mindays":"10"},"k":1,"pctl":{"name":"P1_ProbReach","properties":"const N; const j; \nP = ? [F<=N y=j]\n","arguments":"-const N=200,j=0:1:23"},"result":{"j":"3","value":0.00005850996039789947},"$$hashKey":"object:3181"},{"modeltype":"Pattern_PAM","timecut":{"start":"21","end":"49","mindays":"10"},"k":1,"pctl":{"name":"P1_ProbReach","properties":"const N; const j; \nP = ? [F<=N y=j]\n","arguments":"-const N=200,j=0:1:23"},"result":{"j":"4","value":0.5585871655647024},"$$hashKey":"object:3182"},{"modeltype":"Pattern_PAM","timecut":{"start":"21","end":"49","mindays":"10"},"k":1,"pctl":{"name":"P1_ProbReach","properties":"const N; const j; \nP = ? [F<=N y=j]\n","arguments":"-const N=200,j=0:1:23"},"result":{"j":"5","value":0.9663848871002595},"$$hashKey":"object:3183"},{"modeltype":"Pattern_PAM","timecut":{"start":"21","end":"49","mindays":"10"},"k":1,"pctl":{"name":"P1_ProbReach","properties":"const N; const j; \nP = ? [F<=N y=j]\n","arguments":"-const N=200,j=0:1:23"},"result":{"j":"6","value":1},"$$hashKey":"object:3184"},{"modeltype":"Pattern_PAM","timecut":{"start":"21","end":"49","mindays":"10"},"k":1,"pctl":{"name":"P1_ProbReach","properties":"const N; const j; \nP = ? [F<=N y=j]\n","arguments":"-const N=200,j=0:1:23"},"result":{"j":"7","value":1},"$$hashKey":"object:3185"},{"modeltype":"Pattern_PAM","timecut":{"start":"21","end":"49","mindays":"10"},"k":1,"pctl":{"name":"P1_ProbReach","properties":"const N; const j; \nP = ? [F<=N y=j]\n","arguments":"-const N=200,j=0:1:23"},"result":{"j":"8","value":1},"$$hashKey":"object:3186"},{"modeltype":"Pattern_PAM","timecut":{"start":"21","end":"49","mindays":"10"},"k":1,"pctl":{"name":"P1_ProbReach","properties":"const N; const j; \nP = ? [F<=N y=j]\n","arguments":"-const N=200,j=0:1:23"},"result":{"j":"9","value":1},"$$hashKey":"object:3187"},{"modeltype":"Pattern_PAM","timecut":{"start":"21","end":"49","mindays":"10"},"k":1,"pctl":{"name":"P1_ProbReach","properties":"const N; const j; \nP = ? [F<=N y=j]\n","arguments":"-const N=200,j=0:1:23"},"result":{"j":"10","value":0.9996227201254707},"$$hashKey":"object:3188"},{"modeltype":"Pattern_PAM","timecut":{"start":"21","end":"49","mindays":"10"},"k":1,"pctl":{"name":"P1_ProbReach","properties":"const N; const j; \nP = ? [F<=N y=j]\n","arguments":"-const N=200,j=0:1:23"},"result":{"j":"11","value":0},"$$hashKey":"object:3189"},{"modeltype":"Pattern_PAM","timecut":{"start":"21","end":"49","mindays":"10"},"k":1,"pctl":{"name":"P1_ProbReach","properties":"const N; const j; \nP = ? [F<=N y=j]\n","arguments":"-const N=200,j=0:1:23"},"result":{"j":"12","value":0.31365885533474974},"$$hashKey":"object:3190"},{"modeltype":"Pattern_PAM","timecut":{"start":"21","end":"49","mindays":"10"},"k":1,"pctl":{"name":"P1_ProbReach","properties":"const N; const j; \nP = ? [F<=N y=j]\n","arguments":"-const N=200,j=0:1:23"},"result":{"j":"13","value":0.5858417886562115},"$$hashKey":"object:3191"},{"modeltype":"Pattern_PAM","timecut":{"start":"21","end":"49","mindays":"10"},"k":1,"pctl":{"name":"P1_ProbReach","properties":"const N; const j; \nP = ? [F<=N y=j]\n","arguments":"-const N=200,j=0:1:23"},"result":{"j":"14","value":0.30903076739562646},"$$hashKey":"object:3192"},{"modeltype":"Pattern_PAM","timecut":{"start":"21","end":"49","mindays":"10"},"k":1,"pctl":{"name":"P1_ProbReach","properties":"const N; const j; \nP = ? [F<=N y=j]\n","arguments":"-const N=200,j=0:1:23"},"result":{"j":"15","value":0.9727569871310933},"$$hashKey":"object:3193"},{"modeltype":"Pattern_PAM","timecut":{"start":"21","end":"49","mindays":"10"},"k":1,"pctl":{"name":"P1_ProbReach","properties":"const N; const j; \nP = ? [F<=N y=j]\n","arguments":"-const N=200,j=0:1:23"},"result":{"j":"16","value":0.4036225400786818},"$$hashKey":"object:3194"},{"modeltype":"Pattern_PAM","timecut":{"start":"21","end":"49","mindays":"10"},"k":1,"pctl":{"name":"P1_ProbReach","properties":"const N; const j; \nP = ? [F<=N y=j]\n","arguments":"-const N=200,j=0:1:23"},"result":{"j":"17","value":0.001187282866145215},"$$hashKey":"object:3195"},{"modeltype":"Pattern_PAM","timecut":{"start":"21","end":"49","mindays":"10"},"k":1,"pctl":{"name":"P1_ProbReach","properties":"const N; const j; \nP = ? [F<=N y=j]\n","arguments":"-const N=200,j=0:1:23"},"result":{"j":"18","value":0.9420812010959183},"$$hashKey":"object:3196"},{"modeltype":"Pattern_PAM","timecut":{"start":"21","end":"49","mindays":"10"},"k":1,"pctl":{"name":"P1_ProbReach","properties":"const N; const j; \nP = ? [F<=N y=j]\n","arguments":"-const N=200,j=0:1:23"},"result":{"j":"19","value":0.005247216163702112},"$$hashKey":"object:3197"},{"modeltype":"Pattern_PAM","timecut":{"start":"21","end":"49","mindays":"10"},"k":1,"pctl":{"name":"P1_ProbReach","properties":"const N; const j; \nP = ? [F<=N y=j]\n","arguments":"-const N=200,j=0:1:23"},"result":{"j":"20","value":1},"$$hashKey":"object:3198"},{"modeltype":"Pattern_PAM","timecut":{"start":"21","end":"49","mindays":"10"},"k":1,"pctl":{"name":"P1_ProbReach","properties":"const N; const j; \nP = ? [F<=N y=j]\n","arguments":"-const N=200,j=0:1:23"},"result":{"j":"21","value":0.08216390175248163},"$$hashKey":"object:3199"},{"modeltype":"Pattern_PAM","timecut":{"start":"21","end":"49","mindays":"10"},"k":1,"pctl":{"name":"P1_ProbReach","properties":"const N; const j; \nP = ? [F<=N y=j]\n","arguments":"-const N=200,j=0:1:23"},"result":{"j":"22","value":0.0006086386071462429},"$$hashKey":"object:3200"},{"modeltype":"Pattern_PAM","timecut":{"start":"21","end":"49","mindays":"10"},"k":1,"pctl":{"name":"P1_ProbReach","properties":"const N; const j; \nP = ? [F<=N y=j]\n","arguments":"-const N=200,j=0:1:23"},"result":{"j":"23","value":0.0006055321440009147},"$$hashKey":"object:3201"},{"modeltype":"Pattern_PAM","timecut":{"start":"21","end":"49","mindays":"10"},"k":1,"pctl":{"name":"VisitProbInit","properties":"const int N; const int j; \nP=?[F<=N (y=j)]\n","arguments":"-const N=200,j=0:1:23"},"result":{"j":"0","value":1},"$$hashKey":"object:3226"},{"modeltype":"Pattern_PAM","timecut":{"start":"21","end":"49","mindays":"10"},"k":1,"pctl":{"name":"VisitProbInit","properties":"const int N; const int j; \nP=?[F<=N (y=j)]\n","arguments":"-const N=200,j=0:1:23"},"result":{"j":"1","value":0},"$$hashKey":"object:3227"},{"modeltype":"Pattern_PAM","timecut":{"start":"21","end":"49","mindays":"10"},"k":1,"pctl":{"name":"VisitProbInit","properties":"const int N; const int j; \nP=?[F<=N (y=j)]\n","arguments":"-const N=200,j=0:1:23"},"result":{"j":"2","value":0.04281261706047415},"$$hashKey":"object:3228"},{"modeltype":"Pattern_PAM","timecut":{"start":"21","end":"49","mindays":"10"},"k":1,"pctl":{"name":"VisitProbInit","properties":"const int N; const int j; \nP=?[F<=N (y=j)]\n","arguments":"-const N=200,j=0:1:23"},"result":{"j":"3","value":0.00005850996039789947},"$$hashKey":"object:3229"},{"modeltype":"Pattern_PAM","timecut":{"start":"21","end":"49","mindays":"10"},"k":1,"pctl":{"name":"VisitProbInit","properties":"const int N; const int j; \nP=?[F<=N (y=j)]\n","arguments":"-const N=200,j=0:1:23"},"result":{"j":"4","value":0.5585871655647024},"$$hashKey":"object:3230"},{"modeltype":"Pattern_PAM","timecut":{"start":"21","end":"49","mindays":"10"},"k":1,"pctl":{"name":"VisitProbInit","properties":"const int N; const int j; \nP=?[F<=N (y=j)]\n","arguments":"-const N=200,j=0:1:23"},"result":{"j":"5","value":0.9663848871002595},"$$hashKey":"object:3231"},{"modeltype":"Pattern_PAM","timecut":{"start":"21","end":"49","mindays":"10"},"k":1,"pctl":{"name":"VisitProbInit","properties":"const int N; const int j; \nP=?[F<=N (y=j)]\n","arguments":"-const N=200,j=0:1:23"},"result":{"j":"6","value":1},"$$hashKey":"object:3232"},{"modeltype":"Pattern_PAM","timecut":{"start":"21","end":"49","mindays":"10"},"k":1,"pctl":{"name":"VisitProbInit","properties":"const int N; const int j; \nP=?[F<=N (y=j)]\n","arguments":"-const N=200,j=0:1:23"},"result":{"j":"7","value":1},"$$hashKey":"object:3233"},{"modeltype":"Pattern_PAM","timecut":{"start":"21","end":"49","mindays":"10"},"k":1,"pctl":{"name":"VisitProbInit","properties":"const int N; const int j; \nP=?[F<=N (y=j)]\n","arguments":"-const N=200,j=0:1:23"},"result":{"j":"8","value":1},"$$hashKey":"object:3234"},{"modeltype":"Pattern_PAM","timecut":{"start":"21","end":"49","mindays":"10"},"k":1,"pctl":{"name":"VisitProbInit","properties":"const int N; const int j; \nP=?[F<=N (y=j)]\n","arguments":"-const N=200,j=0:1:23"},"result":{"j":"9","value":1},"$$hashKey":"object:3235"},{"modeltype":"Pattern_PAM","timecut":{"start":"21","end":"49","mindays":"10"},"k":1,"pctl":{"name":"VisitProbInit","properties":"const int N; const int j; \nP=?[F<=N (y=j)]\n","arguments":"-const N=200,j=0:1:23"},"result":{"j":"10","value":0.9996227201254707},"$$hashKey":"object:3236"},{"modeltype":"Pattern_PAM","timecut":{"start":"21","end":"49","mindays":"10"},"k":1,"pctl":{"name":"VisitProbInit","properties":"const int N; const int j; \nP=?[F<=N (y=j)]\n","arguments":"-const N=200,j=0:1:23"},"result":{"j":"11","value":0},"$$hashKey":"object:3237"},{"modeltype":"Pattern_PAM","timecut":{"start":"21","end":"49","mindays":"10"},"k":1,"pctl":{"name":"VisitProbInit","properties":"const int N; const int j; \nP=?[F<=N (y=j)]\n","arguments":"-const N=200,j=0:1:23"},"result":{"j":"12","value":0.31365885533474974},"$$hashKey":"object:3238"},{"modeltype":"Pattern_PAM","timecut":{"start":"21","end":"49","mindays":"10"},"k":1,"pctl":{"name":"VisitProbInit","properties":"const int N; const int j; \nP=?[F<=N (y=j)]\n","arguments":"-const N=200,j=0:1:23"},"result":{"j":"13","value":0.5858417886562115},"$$hashKey":"object:3239"},{"modeltype":"Pattern_PAM","timecut":{"start":"21","end":"49","mindays":"10"},"k":1,"pctl":{"name":"VisitProbInit","properties":"const int N; const int j; \nP=?[F<=N (y=j)]\n","arguments":"-const N=200,j=0:1:23"},"result":{"j":"14","value":0.30903076739562646},"$$hashKey":"object:3240"},{"modeltype":"Pattern_PAM","timecut":{"start":"21","end":"49","mindays":"10"},"k":1,"pctl":{"name":"VisitProbInit","properties":"const int N; const int j; \nP=?[F<=N (y=j)]\n","arguments":"-const N=200,j=0:1:23"},"result":{"j":"15","value":0.9727569871310933},"$$hashKey":"object:3241"},{"modeltype":"Pattern_PAM","timecut":{"start":"21","end":"49","mindays":"10"},"k":1,"pctl":{"name":"VisitProbInit","properties":"const int N; const int j; \nP=?[F<=N (y=j)]\n","arguments":"-const N=200,j=0:1:23"},"result":{"j":"16","value":0.4036225400786818},"$$hashKey":"object:3242"},{"modeltype":"Pattern_PAM","timecut":{"start":"21","end":"49","mindays":"10"},"k":1,"pctl":{"name":"VisitProbInit","properties":"const int N; const int j; \nP=?[F<=N (y=j)]\n","arguments":"-const N=200,j=0:1:23"},"result":{"j":"17","value":0.001187282866145215},"$$hashKey":"object:3243"},{"modeltype":"Pattern_PAM","timecut":{"start":"21","end":"49","mindays":"10"},"k":1,"pctl":{"name":"VisitProbInit","properties":"const int N; const int j; \nP=?[F<=N (y=j)]\n","arguments":"-const N=200,j=0:1:23"},"result":{"j":"18","value":0.9420812010959183},"$$hashKey":"object:3244"},{"modeltype":"Pattern_PAM","timecut":{"start":"21","end":"49","mindays":"10"},"k":1,"pctl":{"name":"VisitProbInit","properties":"const int N; const int j; \nP=?[F<=N (y=j)]\n","arguments":"-const N=200,j=0:1:23"},"result":{"j":"19","value":0.005247216163702112},"$$hashKey":"object:3245"},{"modeltype":"Pattern_PAM","timecut":{"start":"21","end":"49","mindays":"10"},"k":1,"pctl":{"name":"VisitProbInit","properties":"const int N; const int j; \nP=?[F<=N (y=j)]\n","arguments":"-const N=200,j=0:1:23"},"result":{"j":"20","value":1},"$$hashKey":"object:3246"},{"modeltype":"Pattern_PAM","timecut":{"start":"21","end":"49","mindays":"10"},"k":1,"pctl":{"name":"VisitProbInit","properties":"const int N; const int j; \nP=?[F<=N (y=j)]\n","arguments":"-const N=200,j=0:1:23"},"result":{"j":"21","value":0.08216390175248163},"$$hashKey":"object:3247"},{"modeltype":"Pattern_PAM","timecut":{"start":"21","end":"49","mindays":"10"},"k":1,"pctl":{"name":"VisitProbInit","properties":"const int N; const int j; \nP=?[F<=N (y=j)]\n","arguments":"-const N=200,j=0:1:23"},"result":{"j":"22","value":0.0006086386071462429},"$$hashKey":"object:3248"},{"modeltype":"Pattern_PAM","timecut":{"start":"21","end":"49","mindays":"10"},"k":1,"pctl":{"name":"VisitProbInit","properties":"const int N; const int j; \nP=?[F<=N (y=j)]\n","arguments":"-const N=200,j=0:1:23"},"result":{"j":"23","value":0.0006055321440009147},"$$hashKey":"object:3249"},{"modeltype":"Pattern_PAM","timecut":{"start":"21","end":"49","mindays":"10"},"k":1,"pctl":{"name":"StepCountInit","properties":"const int N; const int j; \nR{\"r_Steps\"}=?[F (y=j)]\n","arguments":"-const N=200,j=0:1:23"},"result":{"j":"0","value":0},"$$hashKey":"object:3274"},{"modeltype":"Pattern_PAM","timecut":{"start":"21","end":"49","mindays":"10"},"k":1,"pctl":{"name":"StepCountInit","properties":"const int N; const int j; \nR{\"r_Steps\"}=?[F (y=j)]\n","arguments":"-const N=200,j=0:1:23"},"result":{"j":"1","value":null},"$$hashKey":"object:3275"},{"modeltype":"Pattern_PAM","timecut":{"start":"21","end":"49","mindays":"10"},"k":1,"pctl":{"name":"StepCountInit","properties":"const int N; const int j; \nR{\"r_Steps\"}=?[F (y=j)]\n","arguments":"-const N=200,j=0:1:23"},"result":{"j":"2","value":null},"$$hashKey":"object:3276"},{"modeltype":"Pattern_PAM","timecut":{"start":"21","end":"49","mindays":"10"},"k":1,"pctl":{"name":"StepCountInit","properties":"const int N; const int j; \nR{\"r_Steps\"}=?[F (y=j)]\n","arguments":"-const N=200,j=0:1:23"},"result":{"j":"3","value":null},"$$hashKey":"object:3277"},{"modeltype":"Pattern_PAM","timecut":{"start":"21","end":"49","mindays":"10"},"k":1,"pctl":{"name":"StepCountInit","properties":"const int N; const int j; \nR{\"r_Steps\"}=?[F (y=j)]\n","arguments":"-const N=200,j=0:1:23"},"result":{"j":"4","value":244.98942456639531},"$$hashKey":"object:3278"},{"modeltype":"Pattern_PAM","timecut":{"start":"21","end":"49","mindays":"10"},"k":1,"pctl":{"name":"StepCountInit","properties":"const int N; const int j; \nR{\"r_Steps\"}=?[F (y=j)]\n","arguments":"-const N=200,j=0:1:23"},"result":{"j":"5","value":59.052400789941146},"$$hashKey":"object:3279"},{"modeltype":"Pattern_PAM","timecut":{"start":"21","end":"49","mindays":"10"},"k":1,"pctl":{"name":"StepCountInit","properties":"const int N; const int j; \nR{\"r_Steps\"}=?[F (y=j)]\n","arguments":"-const N=200,j=0:1:23"},"result":{"j":"6","value":7.584069400978115},"$$hashKey":"object:3280"},{"modeltype":"Pattern_PAM","timecut":{"start":"21","end":"49","mindays":"10"},"k":1,"pctl":{"name":"StepCountInit","properties":"const int N; const int j; \nR{\"r_Steps\"}=?[F (y=j)]\n","arguments":"-const N=200,j=0:1:23"},"result":{"j":"7","value":1.4403159119887539},"$$hashKey":"object:3281"},{"modeltype":"Pattern_PAM","timecut":{"start":"21","end":"49","mindays":"10"},"k":1,"pctl":{"name":"StepCountInit","properties":"const int N; const int j; \nR{\"r_Steps\"}=?[F (y=j)]\n","arguments":"-const N=200,j=0:1:23"},"result":{"j":"8","value":3.5519173192468343},"$$hashKey":"object:3282"},{"modeltype":"Pattern_PAM","timecut":{"start":"21","end":"49","mindays":"10"},"k":1,"pctl":{"name":"StepCountInit","properties":"const int N; const int j; \nR{\"r_Steps\"}=?[F (y=j)]\n","arguments":"-const N=200,j=0:1:23"},"result":{"j":"9","value":4.3579485833120835},"$$hashKey":"object:3283"},{"modeltype":"Pattern_PAM","timecut":{"start":"21","end":"49","mindays":"10"},"k":1,"pctl":{"name":"StepCountInit","properties":"const int N; const int j; \nR{\"r_Steps\"}=?[F (y=j)]\n","arguments":"-const N=200,j=0:1:23"},"result":{"j":"10","value":28.40074031037741},"$$hashKey":"object:3284"},{"modeltype":"Pattern_PAM","timecut":{"start":"21","end":"49","mindays":"10"},"k":1,"pctl":{"name":"StepCountInit","properties":"const int N; const int j; \nR{\"r_Steps\"}=?[F (y=j)]\n","arguments":"-const N=200,j=0:1:23"},"result":{"j":"11","value":null},"$$hashKey":"object:3285"},{"modeltype":"Pattern_PAM","timecut":{"start":"21","end":"49","mindays":"10"},"k":1,"pctl":{"name":"StepCountInit","properties":"const int N; const int j; \nR{\"r_Steps\"}=?[F (y=j)]\n","arguments":"-const N=200,j=0:1:23"},"result":{"j":"12","value":535.453592215558},"$$hashKey":"object:3286"},{"modeltype":"Pattern_PAM","timecut":{"start":"21","end":"49","mindays":"10"},"k":1,"pctl":{"name":"StepCountInit","properties":"const int N; const int j; \nR{\"r_Steps\"}=?[F (y=j)]\n","arguments":"-const N=200,j=0:1:23"},"result":{"j":"13","value":227.26533863819307},"$$hashKey":"object:3287"},{"modeltype":"Pattern_PAM","timecut":{"start":"21","end":"49","mindays":"10"},"k":1,"pctl":{"name":"StepCountInit","properties":"const int N; const int j; \nR{\"r_Steps\"}=?[F (y=j)]\n","arguments":"-const N=200,j=0:1:23"},"result":{"j":"14","value":537.1121787078714},"$$hashKey":"object:3288"},{"modeltype":"Pattern_PAM","timecut":{"start":"21","end":"49","mindays":"10"},"k":1,"pctl":{"name":"StepCountInit","properties":"const int N; const int j; \nR{\"r_Steps\"}=?[F (y=j)]\n","arguments":"-const N=200,j=0:1:23"},"result":{"j":"15","value":57.57586165537043},"$$hashKey":"object:3289"},{"modeltype":"Pattern_PAM","timecut":{"start":"21","end":"49","mindays":"10"},"k":1,"pctl":{"name":"StepCountInit","properties":"const int N; const int j; \nR{\"r_Steps\"}=?[F (y=j)]\n","arguments":"-const N=200,j=0:1:23"},"result":{"j":"16","value":385.122577530476},"$$hashKey":"object:3290"},{"modeltype":"Pattern_PAM","timecut":{"start":"21","end":"49","mindays":"10"},"k":1,"pctl":{"name":"StepCountInit","properties":"const int N; const int j; \nR{\"r_Steps\"}=?[F (y=j)]\n","arguments":"-const N=200,j=0:1:23"},"result":{"j":"17","value":null},"$$hashKey":"object:3291"},{"modeltype":"Pattern_PAM","timecut":{"start":"21","end":"49","mindays":"10"},"k":1,"pctl":{"name":"StepCountInit","properties":"const int N; const int j; \nR{\"r_Steps\"}=?[F (y=j)]\n","arguments":"-const N=200,j=0:1:23"},"result":{"j":"18","value":71.38611134553055},"$$hashKey":"object:3292"},{"modeltype":"Pattern_PAM","timecut":{"start":"21","end":"49","mindays":"10"},"k":1,"pctl":{"name":"StepCountInit","properties":"const int N; const int j; \nR{\"r_Steps\"}=?[F (y=j)]\n","arguments":"-const N=200,j=0:1:23"},"result":{"j":"19","value":null},"$$hashKey":"object:3293"},{"modeltype":"Pattern_PAM","timecut":{"start":"21","end":"49","mindays":"10"},"k":1,"pctl":{"name":"StepCountInit","properties":"const int N; const int j; \nR{\"r_Steps\"}=?[F (y=j)]\n","arguments":"-const N=200,j=0:1:23"},"result":{"j":"20","value":2.427917139365596},"$$hashKey":"object:3294"},{"modeltype":"Pattern_PAM","timecut":{"start":"21","end":"49","mindays":"10"},"k":1,"pctl":{"name":"StepCountInit","properties":"const int N; const int j; \nR{\"r_Steps\"}=?[F (y=j)]\n","arguments":"-const N=200,j=0:1:23"},"result":{"j":"21","value":null},"$$hashKey":"object:3295"},{"modeltype":"Pattern_PAM","timecut":{"start":"21","end":"49","mindays":"10"},"k":1,"pctl":{"name":"StepCountInit","properties":"const int N; const int j; \nR{\"r_Steps\"}=?[F (y=j)]\n","arguments":"-const N=200,j=0:1:23"},"result":{"j":"22","value":null},"$$hashKey":"object:3296"},{"modeltype":"Pattern_PAM","timecut":{"start":"21","end":"49","mindays":"10"},"k":1,"pctl":{"name":"StepCountInit","properties":"const int N; const int j; \nR{\"r_Steps\"}=?[F (y=j)]\n","arguments":"-const N=200,j=0:1:23"},"result":{"j":"23","value":null},"$$hashKey":"object:3297"},{"modeltype":"Pattern_PAM","timecut":{"start":"21","end":"49","mindays":"10"},"k":2,"pctl":{"name":"P1_ProbReach","properties":"const N; const j; \nP = ? [F<=N y=j]\n","arguments":"-const N=200,j=0:1:23"},"result":{"j":"0","value":1},"$$hashKey":"object:3322"},{"modeltype":"Pattern_PAM","timecut":{"start":"21","end":"49","mindays":"10"},"k":2,"pctl":{"name":"P1_ProbReach","properties":"const N; const j; \nP = ? [F<=N y=j]\n","arguments":"-const N=200,j=0:1:23"},"result":{"j":"1","value":0},"$$hashKey":"object:3323"},{"modeltype":"Pattern_PAM","timecut":{"start":"21","end":"49","mindays":"10"},"k":2,"pctl":{"name":"P1_ProbReach","properties":"const N; const j; \nP = ? [F<=N y=j]\n","arguments":"-const N=200,j=0:1:23"},"result":{"j":"2","value":0.4615699334716463},"$$hashKey":"object:3324"},{"modeltype":"Pattern_PAM","timecut":{"start":"21","end":"49","mindays":"10"},"k":2,"pctl":{"name":"P1_ProbReach","properties":"const N; const j; \nP = ? [F<=N y=j]\n","arguments":"-const N=200,j=0:1:23"},"result":{"j":"3","value":0.9999523457313265},"$$hashKey":"object:3325"},{"modeltype":"Pattern_PAM","timecut":{"start":"21","end":"49","mindays":"10"},"k":2,"pctl":{"name":"P1_ProbReach","properties":"const N; const j; \nP = ? [F<=N y=j]\n","arguments":"-const N=200,j=0:1:23"},"result":{"j":"4","value":0.23395945881180485},"$$hashKey":"object:3326"},{"modeltype":"Pattern_PAM","timecut":{"start":"21","end":"49","mindays":"10"},"k":2,"pctl":{"name":"P1_ProbReach","properties":"const N; const j; \nP = ? [F<=N y=j]\n","arguments":"-const N=200,j=0:1:23"},"result":{"j":"5","value":0.9808982796971935},"$$hashKey":"object:3327"},{"modeltype":"Pattern_PAM","timecut":{"start":"21","end":"49","mindays":"10"},"k":2,"pctl":{"name":"P1_ProbReach","properties":"const N; const j; \nP = ? [F<=N y=j]\n","arguments":"-const N=200,j=0:1:23"},"result":{"j":"6","value":1},"$$hashKey":"object:3328"},{"modeltype":"Pattern_PAM","timecut":{"start":"21","end":"49","mindays":"10"},"k":2,"pctl":{"name":"P1_ProbReach","properties":"const N; const j; \nP = ? [F<=N y=j]\n","arguments":"-const N=200,j=0:1:23"},"result":{"j":"7","value":1},"$$hashKey":"object:3329"},{"modeltype":"Pattern_PAM","timecut":{"start":"21","end":"49","mindays":"10"},"k":2,"pctl":{"name":"P1_ProbReach","properties":"const N; const j; \nP = ? [F<=N y=j]\n","arguments":"-const N=200,j=0:1:23"},"result":{"j":"8","value":1},"$$hashKey":"object:3330"},{"modeltype":"Pattern_PAM","timecut":{"start":"21","end":"49","mindays":"10"},"k":2,"pctl":{"name":"P1_ProbReach","properties":"const N; const j; \nP = ? [F<=N y=j]\n","arguments":"-const N=200,j=0:1:23"},"result":{"j":"9","value":1},"$$hashKey":"object:3331"},{"modeltype":"Pattern_PAM","timecut":{"start":"21","end":"49","mindays":"10"},"k":2,"pctl":{"name":"P1_ProbReach","properties":"const N; const j; \nP = ? [F<=N y=j]\n","arguments":"-const N=200,j=0:1:23"},"result":{"j":"10","value":0.9949339778956076},"$$hashKey":"object:3332"},{"modeltype":"Pattern_PAM","timecut":{"start":"21","end":"49","mindays":"10"},"k":2,"pctl":{"name":"P1_ProbReach","properties":"const N; const j; \nP = ? [F<=N y=j]\n","arguments":"-const N=200,j=0:1:23"},"result":{"j":"11","value":0},"$$hashKey":"object:3333"},{"modeltype":"Pattern_PAM","timecut":{"start":"21","end":"49","mindays":"10"},"k":2,"pctl":{"name":"P1_ProbReach","properties":"const N; const j; \nP = ? [F<=N y=j]\n","arguments":"-const N=200,j=0:1:23"},"result":{"j":"12","value":0.4078984216418919},"$$hashKey":"object:3334"},{"modeltype":"Pattern_PAM","timecut":{"start":"21","end":"49","mindays":"10"},"k":2,"pctl":{"name":"P1_ProbReach","properties":"const N; const j; \nP = ? [F<=N y=j]\n","arguments":"-const N=200,j=0:1:23"},"result":{"j":"13","value":0.9360656760641057},"$$hashKey":"object:3335"},{"modeltype":"Pattern_PAM","timecut":{"start":"21","end":"49","mindays":"10"},"k":2,"pctl":{"name":"P1_ProbReach","properties":"const N; const j; \nP = ? [F<=N y=j]\n","arguments":"-const N=200,j=0:1:23"},"result":{"j":"14","value":0.17820361204566454},"$$hashKey":"object:3336"},{"modeltype":"Pattern_PAM","timecut":{"start":"21","end":"49","mindays":"10"},"k":2,"pctl":{"name":"P1_ProbReach","properties":"const N; const j; \nP = ? [F<=N y=j]\n","arguments":"-const N=200,j=0:1:23"},"result":{"j":"15","value":0.986417738703077},"$$hashKey":"object:3337"},{"modeltype":"Pattern_PAM","timecut":{"start":"21","end":"49","mindays":"10"},"k":2,"pctl":{"name":"P1_ProbReach","properties":"const N; const j; \nP = ? [F<=N y=j]\n","arguments":"-const N=200,j=0:1:23"},"result":{"j":"16","value":0.5667075813270683},"$$hashKey":"object:3338"},{"modeltype":"Pattern_PAM","timecut":{"start":"21","end":"49","mindays":"10"},"k":2,"pctl":{"name":"P1_ProbReach","properties":"const N; const j; \nP = ? [F<=N y=j]\n","arguments":"-const N=200,j=0:1:23"},"result":{"j":"17","value":0.005940646290550208},"$$hashKey":"object:3339"},{"modeltype":"Pattern_PAM","timecut":{"start":"21","end":"49","mindays":"10"},"k":2,"pctl":{"name":"P1_ProbReach","properties":"const N; const j; \nP = ? [F<=N y=j]\n","arguments":"-const N=200,j=0:1:23"},"result":{"j":"18","value":0.8833104550960309},"$$hashKey":"object:3340"},{"modeltype":"Pattern_PAM","timecut":{"start":"21","end":"49","mindays":"10"},"k":2,"pctl":{"name":"P1_ProbReach","properties":"const N; const j; \nP = ? [F<=N y=j]\n","arguments":"-const N=200,j=0:1:23"},"result":{"j":"19","value":0.007215627971030478},"$$hashKey":"object:3341"},{"modeltype":"Pattern_PAM","timecut":{"start":"21","end":"49","mindays":"10"},"k":2,"pctl":{"name":"P1_ProbReach","properties":"const N; const j; \nP = ? [F<=N y=j]\n","arguments":"-const N=200,j=0:1:23"},"result":{"j":"20","value":1},"$$hashKey":"object:3342"},{"modeltype":"Pattern_PAM","timecut":{"start":"21","end":"49","mindays":"10"},"k":2,"pctl":{"name":"P1_ProbReach","properties":"const N; const j; \nP = ? [F<=N y=j]\n","arguments":"-const N=200,j=0:1:23"},"result":{"j":"21","value":0.14154369648778986},"$$hashKey":"object:3343"},{"modeltype":"Pattern_PAM","timecut":{"start":"21","end":"49","mindays":"10"},"k":2,"pctl":{"name":"P1_ProbReach","properties":"const N; const j; \nP = ? [F<=N y=j]\n","arguments":"-const N=200,j=0:1:23"},"result":{"j":"22","value":0.0030198066277848665},"$$hashKey":"object:3344"},{"modeltype":"Pattern_PAM","timecut":{"start":"21","end":"49","mindays":"10"},"k":2,"pctl":{"name":"P1_ProbReach","properties":"const N; const j; \nP = ? [F<=N y=j]\n","arguments":"-const N=200,j=0:1:23"},"result":{"j":"23","value":0.002645200547103275},"$$hashKey":"object:3345"},{"modeltype":"Pattern_PAM","timecut":{"start":"21","end":"49","mindays":"10"},"k":2,"pctl":{"name":"VisitProbInit","properties":"const int N; const int j; \nP=?[F<=N (y=j)]\n","arguments":"-const N=200,j=0:1:23"},"result":{"j":"0","value":1},"$$hashKey":"object:3370"},{"modeltype":"Pattern_PAM","timecut":{"start":"21","end":"49","mindays":"10"},"k":2,"pctl":{"name":"VisitProbInit","properties":"const int N; const int j; \nP=?[F<=N (y=j)]\n","arguments":"-const N=200,j=0:1:23"},"result":{"j":"1","value":0},"$$hashKey":"object:3371"},{"modeltype":"Pattern_PAM","timecut":{"start":"21","end":"49","mindays":"10"},"k":2,"pctl":{"name":"VisitProbInit","properties":"const int N; const int j; \nP=?[F<=N (y=j)]\n","arguments":"-const N=200,j=0:1:23"},"result":{"j":"2","value":0.4615699334716463},"$$hashKey":"object:3372"},{"modeltype":"Pattern_PAM","timecut":{"start":"21","end":"49","mindays":"10"},"k":2,"pctl":{"name":"VisitProbInit","properties":"const int N; const int j; \nP=?[F<=N (y=j)]\n","arguments":"-const N=200,j=0:1:23"},"result":{"j":"3","value":0.9999523457313265},"$$hashKey":"object:3373"},{"modeltype":"Pattern_PAM","timecut":{"start":"21","end":"49","mindays":"10"},"k":2,"pctl":{"name":"VisitProbInit","properties":"const int N; const int j; \nP=?[F<=N (y=j)]\n","arguments":"-const N=200,j=0:1:23"},"result":{"j":"4","value":0.23395945881180485},"$$hashKey":"object:3374"},{"modeltype":"Pattern_PAM","timecut":{"start":"21","end":"49","mindays":"10"},"k":2,"pctl":{"name":"VisitProbInit","properties":"const int N; const int j; \nP=?[F<=N (y=j)]\n","arguments":"-const N=200,j=0:1:23"},"result":{"j":"5","value":0.9808982796971935},"$$hashKey":"object:3375"},{"modeltype":"Pattern_PAM","timecut":{"start":"21","end":"49","mindays":"10"},"k":2,"pctl":{"name":"VisitProbInit","properties":"const int N; const int j; \nP=?[F<=N (y=j)]\n","arguments":"-const N=200,j=0:1:23"},"result":{"j":"6","value":1},"$$hashKey":"object:3376"},{"modeltype":"Pattern_PAM","timecut":{"start":"21","end":"49","mindays":"10"},"k":2,"pctl":{"name":"VisitProbInit","properties":"const int N; const int j; \nP=?[F<=N (y=j)]\n","arguments":"-const N=200,j=0:1:23"},"result":{"j":"7","value":1},"$$hashKey":"object:3377"},{"modeltype":"Pattern_PAM","timecut":{"start":"21","end":"49","mindays":"10"},"k":2,"pctl":{"name":"VisitProbInit","properties":"const int N; const int j; \nP=?[F<=N (y=j)]\n","arguments":"-const N=200,j=0:1:23"},"result":{"j":"8","value":1},"$$hashKey":"object:3378"},{"modeltype":"Pattern_PAM","timecut":{"start":"21","end":"49","mindays":"10"},"k":2,"pctl":{"name":"VisitProbInit","properties":"const int N; const int j; \nP=?[F<=N (y=j)]\n","arguments":"-const N=200,j=0:1:23"},"result":{"j":"9","value":1},"$$hashKey":"object:3379"},{"modeltype":"Pattern_PAM","timecut":{"start":"21","end":"49","mindays":"10"},"k":2,"pctl":{"name":"VisitProbInit","properties":"const int N; const int j; \nP=?[F<=N (y=j)]\n","arguments":"-const N=200,j=0:1:23"},"result":{"j":"10","value":0.9949339778956076},"$$hashKey":"object:3380"},{"modeltype":"Pattern_PAM","timecut":{"start":"21","end":"49","mindays":"10"},"k":2,"pctl":{"name":"VisitProbInit","properties":"const int N; const int j; \nP=?[F<=N (y=j)]\n","arguments":"-const N=200,j=0:1:23"},"result":{"j":"11","value":0},"$$hashKey":"object:3381"},{"modeltype":"Pattern_PAM","timecut":{"start":"21","end":"49","mindays":"10"},"k":2,"pctl":{"name":"VisitProbInit","properties":"const int N; const int j; \nP=?[F<=N (y=j)]\n","arguments":"-const N=200,j=0:1:23"},"result":{"j":"12","value":0.4078984216418919},"$$hashKey":"object:3382"},{"modeltype":"Pattern_PAM","timecut":{"start":"21","end":"49","mindays":"10"},"k":2,"pctl":{"name":"VisitProbInit","properties":"const int N; const int j; \nP=?[F<=N (y=j)]\n","arguments":"-const N=200,j=0:1:23"},"result":{"j":"13","value":0.9360656760641057},"$$hashKey":"object:3383"},{"modeltype":"Pattern_PAM","timecut":{"start":"21","end":"49","mindays":"10"},"k":2,"pctl":{"name":"VisitProbInit","properties":"const int N; const int j; \nP=?[F<=N (y=j)]\n","arguments":"-const N=200,j=0:1:23"},"result":{"j":"14","value":0.17820361204566454},"$$hashKey":"object:3384"},{"modeltype":"Pattern_PAM","timecut":{"start":"21","end":"49","mindays":"10"},"k":2,"pctl":{"name":"VisitProbInit","properties":"const int N; const int j; \nP=?[F<=N (y=j)]\n","arguments":"-const N=200,j=0:1:23"},"result":{"j":"15","value":0.986417738703077},"$$hashKey":"object:3385"},{"modeltype":"Pattern_PAM","timecut":{"start":"21","end":"49","mindays":"10"},"k":2,"pctl":{"name":"VisitProbInit","properties":"const int N; const int j; \nP=?[F<=N (y=j)]\n","arguments":"-const N=200,j=0:1:23"},"result":{"j":"16","value":0.5667075813270683},"$$hashKey":"object:3386"},{"modeltype":"Pattern_PAM","timecut":{"start":"21","end":"49","mindays":"10"},"k":2,"pctl":{"name":"VisitProbInit","properties":"const int N; const int j; \nP=?[F<=N (y=j)]\n","arguments":"-const N=200,j=0:1:23"},"result":{"j":"17","value":0.005940646290550208},"$$hashKey":"object:3387"},{"modeltype":"Pattern_PAM","timecut":{"start":"21","end":"49","mindays":"10"},"k":2,"pctl":{"name":"VisitProbInit","properties":"const int N; const int j; \nP=?[F<=N (y=j)]\n","arguments":"-const N=200,j=0:1:23"},"result":{"j":"18","value":0.8833104550960309},"$$hashKey":"object:3388"},{"modeltype":"Pattern_PAM","timecut":{"start":"21","end":"49","mindays":"10"},"k":2,"pctl":{"name":"VisitProbInit","properties":"const int N; const int j; \nP=?[F<=N (y=j)]\n","arguments":"-const N=200,j=0:1:23"},"result":{"j":"19","value":0.007215627971030478},"$$hashKey":"object:3389"},{"modeltype":"Pattern_PAM","timecut":{"start":"21","end":"49","mindays":"10"},"k":2,"pctl":{"name":"VisitProbInit","properties":"const int N; const int j; \nP=?[F<=N (y=j)]\n","arguments":"-const N=200,j=0:1:23"},"result":{"j":"20","value":1},"$$hashKey":"object:3390"},{"modeltype":"Pattern_PAM","timecut":{"start":"21","end":"49","mindays":"10"},"k":2,"pctl":{"name":"VisitProbInit","properties":"const int N; const int j; \nP=?[F<=N (y=j)]\n","arguments":"-const N=200,j=0:1:23"},"result":{"j":"21","value":0.14154369648778986},"$$hashKey":"object:3391"},{"modeltype":"Pattern_PAM","timecut":{"start":"21","end":"49","mindays":"10"},"k":2,"pctl":{"name":"VisitProbInit","properties":"const int N; const int j; \nP=?[F<=N (y=j)]\n","arguments":"-const N=200,j=0:1:23"},"result":{"j":"22","value":0.0030198066277848665},"$$hashKey":"object:3392"},{"modeltype":"Pattern_PAM","timecut":{"start":"21","end":"49","mindays":"10"},"k":2,"pctl":{"name":"VisitProbInit","properties":"const int N; const int j; \nP=?[F<=N (y=j)]\n","arguments":"-const N=200,j=0:1:23"},"result":{"j":"23","value":0.002645200547103275},"$$hashKey":"object:3393"},{"modeltype":"Pattern_PAM","timecut":{"start":"21","end":"49","mindays":"10"},"k":2,"pctl":{"name":"StepCountInit","properties":"const int N; const int j; \nR{\"r_Steps\"}=?[F (y=j)]\n","arguments":"-const N=200,j=0:1:23"},"result":{"j":"0","value":0}},{"modeltype":"Pattern_PAM","timecut":{"start":"21","end":"49","mindays":"10"},"k":2,"pctl":{"name":"StepCountInit","properties":"const int N; const int j; \nR{\"r_Steps\"}=?[F (y=j)]\n","arguments":"-const N=200,j=0:1:23"},"result":{"j":"1","value":null}},{"modeltype":"Pattern_PAM","timecut":{"start":"21","end":"49","mindays":"10"},"k":2,"pctl":{"name":"StepCountInit","properties":"const int N; const int j; \nR{\"r_Steps\"}=?[F (y=j)]\n","arguments":"-const N=200,j=0:1:23"},"result":{"j":"2","value":323.0966184859274}},{"modeltype":"Pattern_PAM","timecut":{"start":"21","end":"49","mindays":"10"},"k":2,"pctl":{"name":"StepCountInit","properties":"const int N; const int j; \nR{\"r_Steps\"}=?[F (y=j)]\n","arguments":"-const N=200,j=0:1:23"},"result":{"j":"3","value":17.579044282146352}},{"modeltype":"Pattern_PAM","timecut":{"start":"21","end":"49","mindays":"10"},"k":2,"pctl":{"name":"StepCountInit","properties":"const int N; const int j; \nR{\"r_Steps\"}=?[F (y=j)]\n","arguments":"-const N=200,j=0:1:23"},"result":{"j":"4","value":795.1438402383988}},{"modeltype":"Pattern_PAM","timecut":{"start":"21","end":"49","mindays":"10"},"k":2,"pctl":{"name":"StepCountInit","properties":"const int N; const int j; \nR{\"r_Steps\"}=?[F (y=j)]\n","arguments":"-const N=200,j=0:1:23"},"result":{"j":"5","value":47.813360848128326}},{"modeltype":"Pattern_PAM","timecut":{"start":"21","end":"49","mindays":"10"},"k":2,"pctl":{"name":"StepCountInit","properties":"const int N; const int j; \nR{\"r_Steps\"}=?[F (y=j)]\n","arguments":"-const N=200,j=0:1:23"},"result":{"j":"6","value":6.20705480553764}},{"modeltype":"Pattern_PAM","timecut":{"start":"21","end":"49","mindays":"10"},"k":2,"pctl":{"name":"StepCountInit","properties":"const int N; const int j; \nR{\"r_Steps\"}=?[F (y=j)]\n","arguments":"-const N=200,j=0:1:23"},"result":{"j":"7","value":2.1718244588511486}},{"modeltype":"Pattern_PAM","timecut":{"start":"21","end":"49","mindays":"10"},"k":2,"pctl":{"name":"StepCountInit","properties":"const int N; const int j; \nR{\"r_Steps\"}=?[F (y=j)]\n","arguments":"-const N=200,j=0:1:23"},"result":{"j":"8","value":3.7439365401546474}},{"modeltype":"Pattern_PAM","timecut":{"start":"21","end":"49","mindays":"10"},"k":2,"pctl":{"name":"StepCountInit","properties":"const int N; const int j; \nR{\"r_Steps\"}=?[F (y=j)]\n","arguments":"-const N=200,j=0:1:23"},"result":{"j":"9","value":4.742681202905803}},{"modeltype":"Pattern_PAM","timecut":{"start":"21","end":"49","mindays":"10"},"k":2,"pctl":{"name":"StepCountInit","properties":"const int N; const int j; \nR{\"r_Steps\"}=?[F (y=j)]\n","arguments":"-const N=200,j=0:1:23"},"result":{"j":"10","value":39.11635851150619}},{"modeltype":"Pattern_PAM","timecut":{"start":"21","end":"49","mindays":"10"},"k":2,"pctl":{"name":"StepCountInit","properties":"const int N; const int j; \nR{\"r_Steps\"}=?[F (y=j)]\n","arguments":"-const N=200,j=0:1:23"},"result":{"j":"11","value":null}},{"modeltype":"Pattern_PAM","timecut":{"start":"21","end":"49","mindays":"10"},"k":2,"pctl":{"name":"StepCountInit","properties":"const int N; const int j; \nR{\"r_Steps\"}=?[F (y=j)]\n","arguments":"-const N=200,j=0:1:23"},"result":{"j":"12","value":384.18419663323056}},{"modeltype":"Pattern_PAM","timecut":{"start":"21","end":"49","mindays":"10"},"k":2,"pctl":{"name":"StepCountInit","properties":"const int N; const int j; \nR{\"r_Steps\"}=?[F (y=j)]\n","arguments":"-const N=200,j=0:1:23"},"result":{"j":"13","value":72.59662156270673}},{"modeltype":"Pattern_PAM","timecut":{"start":"21","end":"49","mindays":"10"},"k":2,"pctl":{"name":"StepCountInit","properties":"const int N; const int j; \nR{\"r_Steps\"}=?[F (y=j)]\n","arguments":"-const N=200,j=0:1:23"},"result":{"j":"14","value":1063.8141317313778}},{"modeltype":"Pattern_PAM","timecut":{"start":"21","end":"49","mindays":"10"},"k":2,"pctl":{"name":"StepCountInit","properties":"const int N; const int j; \nR{\"r_Steps\"}=?[F (y=j)]\n","arguments":"-const N=200,j=0:1:23"},"result":{"j":"15","value":48.86925388748296}},{"modeltype":"Pattern_PAM","timecut":{"start":"21","end":"49","mindays":"10"},"k":2,"pctl":{"name":"StepCountInit","properties":"const int N; const int j; \nR{\"r_Steps\"}=?[F (y=j)]\n","arguments":"-const N=200,j=0:1:23"},"result":{"j":"16","value":239.68137465403674}},{"modeltype":"Pattern_PAM","timecut":{"start":"21","end":"49","mindays":"10"},"k":2,"pctl":{"name":"StepCountInit","properties":"const int N; const int j; \nR{\"r_Steps\"}=?[F (y=j)]\n","arguments":"-const N=200,j=0:1:23"},"result":{"j":"17","value":null}},{"modeltype":"Pattern_PAM","timecut":{"start":"21","end":"49","mindays":"10"},"k":2,"pctl":{"name":"StepCountInit","properties":"const int N; const int j; \nR{\"r_Steps\"}=?[F (y=j)]\n","arguments":"-const N=200,j=0:1:23"},"result":{"j":"18","value":93.72702157952834}},{"modeltype":"Pattern_PAM","timecut":{"start":"21","end":"49","mindays":"10"},"k":2,"pctl":{"name":"StepCountInit","properties":"const int N; const int j; \nR{\"r_Steps\"}=?[F (y=j)]\n","arguments":"-const N=200,j=0:1:23"},"result":{"j":"19","value":null}},{"modeltype":"Pattern_PAM","timecut":{"start":"21","end":"49","mindays":"10"},"k":2,"pctl":{"name":"StepCountInit","properties":"const int N; const int j; \nR{\"r_Steps\"}=?[F (y=j)]\n","arguments":"-const N=200,j=0:1:23"},"result":{"j":"20","value":5.928403505600614}},{"modeltype":"Pattern_PAM","timecut":{"start":"21","end":"49","mindays":"10"},"k":2,"pctl":{"name":"StepCountInit","properties":"const int N; const int j; \nR{\"r_Steps\"}=?[F (y=j)]\n","arguments":"-const N=200,j=0:1:23"},"result":{"j":"21","value":1314.1772194068683}},{"modeltype":"Pattern_PAM","timecut":{"start":"21","end":"49","mindays":"10"},"k":2,"pctl":{"name":"StepCountInit","properties":"const int N; const int j; \nR{\"r_Steps\"}=?[F (y=j)]\n","arguments":"-const N=200,j=0:1:23"},"result":{"j":"22","value":null}},{"modeltype":"Pattern_PAM","timecut":{"start":"21","end":"49","mindays":"10"},"k":2,"pctl":{"name":"StepCountInit","properties":"const int N; const int j; \nR{\"r_Steps\"}=?[F (y=j)]\n","arguments":"-const N=200,j=0:1:23"},"result":{"j":"23","value":null}}]